vunv79_utilities/__init__.py
vunv79_utilities/libs/__init__.py
vunv79_utilities/libs/helpers/__init__.py
vunv79_utilities/libs/helpers/metaclass.py
vunv79_utilities/libs/kafka/__init__.py
vunv79_utilities/libs/kafka/consumer.py
vunv79_utilities/libs/kafka/producer.py
vunv79_utilities/libs/logger/__init__.py
vunv79_utilities/libs/logger/setup.py
vunv79_utilities/libs/telegram/__init__.py
vunv79_utilities/libs/telegram/channel.py
vunv79_utilities/libs/telegram/config.py
vunv79_utilities-1.0.3.dist-info/LICENSE
vunv79_utilities-1.0.3.dist-info/METADATA
vunv79_utilities-1.0.3.dist-info/WHEEL
vunv79_utilities-1.0.3.dist-info/top_level.txt
vunv79_utilities-1.0.3.dist-info/RECORD
